githubcollaborators/__init__.py
githubcollaborators-0.0.1.data/scripts/githubcollaborators
githubcollaborators-0.0.1.dist-info/LICENSE
githubcollaborators-0.0.1.dist-info/METADATA
githubcollaborators-0.0.1.dist-info/WHEEL
githubcollaborators-0.0.1.dist-info/top_level.txt
githubcollaborators-0.0.1.dist-info/RECORD
