Metadata-Version: 2.1
Name: githubcollaborators
Version: 0.0.1
Summary: List collaborators for all of a user's repositories.
Home-page: https://github.com/marcolussetti/githubcollaborators
Author: Marco Lussetti
Author-email: packages@marcolussetti.com
License: UNKNOWN
Platform: UNKNOWN
Classifier: Programming Language :: Python :: 3
Classifier: License :: OSI Approved :: MIT License
Classifier: Operating System :: OS Independent
Requires-Python: >=3.6
Requires-Dist: requests
